<?xml version="1.0"?>
<!DOCTYPE hibernate-mapping PUBLIC "-//Hibernate/Hibernate Mapping DTD 3.0//EN"
"http://hibernate.sourceforge.net/hibernate-mapping-3.0.dtd">
<!-- Generated 29 oct. 2014 23:39:21 by Hibernate Tools 3.4.0.CR1 -->
<hibernate-mapping>
    <class name="Customers" table="CUSTOMERS">
        <comment>dimension table</comment>
        <id name="custId" type="big_decimal">
            <column name="CUST_ID" precision="22" scale="0" />
            <generator class="assigned" />
        </id>
        <many-to-one name="countries" class="Countries" fetch="select">
            <column name="COUNTRY_ID" precision="22" scale="0" not-null="true">
                <comment>foreign key to the countries table (snowflake)</comment>
            </column>
        </many-to-one>
        <property name="custFirstName" type="string">
            <column name="CUST_FIRST_NAME" length="20" not-null="true">
                <comment>first name of the customer</comment>
            </column>
        </property>
        <property name="custLastName" type="string">
            <column name="CUST_LAST_NAME" length="40" not-null="true">
                <comment>last name of the customer</comment>
            </column>
        </property>
        <property name="custGender" type="char">
            <column name="CUST_GENDER" length="1" not-null="true">
                <comment>gender; low cardinality attribute</comment>
            </column>
        </property>
        <property name="custYearOfBirth" type="short">
            <column name="CUST_YEAR_OF_BIRTH" precision="4" scale="0" not-null="true">
                <comment>customer year of birth</comment>
            </column>
        </property>
        <property name="custMaritalStatus" type="string">
            <column name="CUST_MARITAL_STATUS" length="20">
                <comment>customer marital status; low cardinality attribute</comment>
            </column>
        </property>
        <property name="custStreetAddress" type="string">
            <column name="CUST_STREET_ADDRESS" length="40" not-null="true">
                <comment>customer street address</comment>
            </column>
        </property>
        <property name="custPostalCode" type="string">
            <column name="CUST_POSTAL_CODE" length="10" not-null="true">
                <comment>postal code of the customer</comment>
            </column>
        </property>
        <property name="custCity" type="string">
            <column name="CUST_CITY" length="30" not-null="true">
                <comment>city where the customer lives</comment>
            </column>
        </property>
        <property name="custCityId" type="big_decimal">
            <column name="CUST_CITY_ID" precision="22" scale="0" not-null="true" />
        </property>
        <property name="custStateProvince" type="string">
            <column name="CUST_STATE_PROVINCE" length="40" not-null="true">
                <comment>customer geography: state or province</comment>
            </column>
        </property>
        <property name="custStateProvinceId" type="big_decimal">
            <column name="CUST_STATE_PROVINCE_ID" precision="22" scale="0" not-null="true" />
        </property>
        <property name="custMainPhoneNumber" type="string">
            <column name="CUST_MAIN_PHONE_NUMBER" length="25" not-null="true">
                <comment>customer main phone number</comment>
            </column>
        </property>
        <property name="custIncomeLevel" type="string">
            <column name="CUST_INCOME_LEVEL" length="30">
                <comment>customer income level</comment>
            </column>
        </property>
        <property name="custCreditLimit" type="big_decimal">
            <column name="CUST_CREDIT_LIMIT" precision="22" scale="0">
                <comment>customer credit limit</comment>
            </column>
        </property>
        <property name="custEmail" type="string">
            <column name="CUST_EMAIL" length="50">
                <comment>customer email id</comment>
            </column>
        </property>
        <property name="custTotal" type="string">
            <column name="CUST_TOTAL" length="14" not-null="true" />
        </property>
        <property name="custTotalId" type="big_decimal">
            <column name="CUST_TOTAL_ID" precision="22" scale="0" not-null="true" />
        </property>
        <property name="custSrcId" type="big_decimal">
            <column name="CUST_SRC_ID" precision="22" scale="0" />
        </property>
        <property name="custEffFrom" type="date">
            <column name="CUST_EFF_FROM" length="7" />
        </property>
        <property name="custEffTo" type="date">
            <column name="CUST_EFF_TO" length="7" />
        </property>
        <property name="custValid" type="string">
            <column name="CUST_VALID" length="1" />
        </property>
        <set name="saleses" table="SALES" inverse="true" lazy="true" fetch="select">
            <key>
                <column name="CUST_ID" precision="22" scale="0" not-null="true">
                    <comment>FK to the customers dimension table</comment>
                </column>
            </key>
            <one-to-many class="Sales" />
        </set>
    </class>
</hibernate-mapping>
